oresme/__init__.py
oresme/_version.py
oresme/oresme.py
oresme-0.1.0.dist-info/licenses/LICENSE
oresme-0.1.0.dist-info/METADATA
oresme-0.1.0.dist-info/WHEEL
oresme-0.1.0.dist-info/top_level.txt
oresme-0.1.0.dist-info/RECORD
