Metadata-Version: 2.4
Name: oresme
Version: 0.1.0
Summary: Oresme numbers refer to the sums related to the harmonic series
Home-page: https://github.com/WhiteSymmetry/Oresme
Author: Mehmet Keçeci
Author-email: Mehmet Keçeci <mkececi@yaani.com>
License: MIT License
Project-URL: Homepage, https://github.com/WhiteSymmetry/Oresme/
Project-URL: Documentation, https://WhiteSymmetry.github.io/Oresme/
Project-URL: Repository, https://github.com/WhiteSymmetry/Oresme/
Project-URL: Issues, https://github.com/WhiteSymmetry/Oresme/issues
Keywords: Oresme
Classifier: Programming Language :: Python :: 3
Classifier: Operating System :: OS Independent
Classifier: Topic :: Software Development
Classifier: Topic :: Scientific/Engineering
Classifier: Typing :: Typed
Classifier: Operating System :: Microsoft :: Windows
Classifier: Operating System :: POSIX
Classifier: Operating System :: Unix
Classifier: Operating System :: MacOS
Classifier: License :: OSI Approved :: MIT License
Classifier: Intended Audience :: Developers
Classifier: Intended Audience :: Science/Research
Requires-Python: >=3.9
License-File: LICENSE
Dynamic: author
Dynamic: home-page
Dynamic: license-file
Dynamic: requires-python
